Metadata-Version: 2.1
Name: nonebot-plugin-chatrecorder-guild-patch
Version: 0.1.2
Summary: nonebot-plugin-chatrecorder的频道适配器
Home-page: https://github.com/X-Skirt-X/nonebot-plugin-chatrecorder-guild-patch
Author: MYXS
Author-email: 1964324406@qq.com
License: UNKNOWN
Platform: UNKNOWN
